<?xml version="1.0" encoding="UTF-8"?>
<LanguageData>

    <!-- группа -->
    <ApparelPermitTitle.label>одежда и аксесссуары</ApparelPermitTitle.label>
    <ApparelPermitTitle.description>Запрос доставки различной одежды и аксесссуаров.</ApparelPermitTitle.description>
    <WorkerPermitSmallTitle.label>одежда для рабочих</WorkerPermitSmallTitle.label>
    <WorkerPermitSmallTitle.description>Запрос доставки различной одежды для рабочих.</WorkerPermitSmallTitle.description>
    <SpecialPermitSmallTitle.label>спецодежда</SpecialPermitSmallTitle.label>
    <SpecialPermitSmallTitle.description>Запрос доставки различной одежды для солдат и дворянства.</SpecialPermitSmallTitle.description>
    
    <!-- солдатское -->
    <SoldierAccessoriesDrop.label>набор штурмовика</SoldierAccessoriesDrop.label>
    <SoldierAccessoriesDrop.description>Запрос доставки набора аксесссуаров для штурмовика. Полная броня не входит в комплект.</SoldierAccessoriesDrop.description>
    <SoldierAccessoriesAltDrop.label>набор разведчика</SoldierAccessoriesAltDrop.label>
    <SoldierAccessoriesAltDrop.description>Запрос доставки набора аксесссуаров для разведчика. Полная броня не входит в комплект.</SoldierAccessoriesAltDrop.description>

    <!-- обычное -->
    <SmithOutfitDrop.label>одежда кузнеца</SmithOutfitDrop.label>
    <SmithOutfitDrop.description>Запрос доставки набора одежды кузнеца.</SmithOutfitDrop.description>
    <FarmerOutfitDrop.label>одежда фермера</FarmerOutfitDrop.label>
    <FarmerOutfitDrop.description>Запрос доставки набора одежды фермера.</FarmerOutfitDrop.description>

    <ChefOutfitDrop.label>одежда повара</ChefOutfitDrop.label>
    <ChefOutfitDrop.description>Запрос доставки набора одежды повара.</ChefOutfitDrop.description>
    <MedicOutfitDrop.label>одежда врача</MedicOutfitDrop.label>
    <MedicOutfitDrop.description>Запрос доставки набора одежды врача.</MedicOutfitDrop.description>

    <MinerOutfitDrop.label>одежда шахтёра</MinerOutfitDrop.label>
    <MinerOutfitDrop.description>Запрос доставки набора одежды шахтёра.</MinerOutfitDrop.description>
    <ConstructorOutfitDrop.label>одежда строителя</ConstructorOutfitDrop.label>
    <ConstructorOutfitDrop.description>Запрос доставки набора одежды строителя.</ConstructorOutfitDrop.description>

    <SlaveOutfitDrop.label>одежда раба</SlaveOutfitDrop.label>
    <SlaveOutfitDrop.description>Запрос доставки набора одежды раба.</SlaveOutfitDrop.description>
    <HazmatOutfitDrop.label>набор химзащиты</HazmatOutfitDrop.label>
    <HazmatOutfitDrop.description>Запрос доставки набора химзащиты.</HazmatOutfitDrop.description>

    <RoyalOutfitDrop.label>одеяния знати</RoyalOutfitDrop.label>
    <RoyalOutfitDrop.description>Запрос доставки набора одеяния знати.</RoyalOutfitDrop.description>
    <PsychicOutfitDrop.label>одежда из элтекса</PsychicOutfitDrop.label>
    <PsychicOutfitDrop.description>Запрос доставки набора одежды из элтекса.</PsychicOutfitDrop.description>

</LanguageData>